__init__.py
brew_tools/__init__.py
brew_tools/brew_maths.py
brew_tools/command_line.py
brew_tools/config.py
brew_tools/converter.py
brew_tools/inputs.py
brew_tools-0.6.0.dist-info/AUTHORS.rst
brew_tools-0.6.0.dist-info/LICENSE.txt
brew_tools-0.6.0.dist-info/METADATA
brew_tools-0.6.0.dist-info/WHEEL
brew_tools-0.6.0.dist-info/entry_points.txt
brew_tools-0.6.0.dist-info/top_level.txt
brew_tools-0.6.0.dist-info/RECORD
