Metadata-Version: 2.1
Name: brew-tools
Version: 0.6.0
Summary: Add your description here
Requires-Python: >=3.12
License-File: LICENSE.txt
License-File: AUTHORS.rst
Requires-Dist: appdirs >=1.4.4
Requires-Dist: click >=8.1.7
